Pandas_Data_Exploration_Utility_Package-0.0.3.dist-info/METADATA
Pandas_Data_Exploration_Utility_Package-0.0.3.dist-info/RECORD
Pandas_Data_Exploration_Utility_Package-0.0.3.dist-info/WHEEL
Pandas_Data_Exploration_Utility_Package-0.0.3.dist-info/top_level.txt
pandas_exploration_util/__init__.py
pandas_exploration_util/stats.py
pandas_exploration_util/viz/__init__.py
pandas_exploration_util/viz/explore.py
