Metadata-Version: 2.1
Name: Pandas-Data-Exploration-Utility-Package
Version: 0.0.3
Summary: Utility functions to help with exploratory data analysis on top the Pandas APIs
Home-page: https://github.com/yifeihuang/pandas_exploration_util
Author: Yifei Huang
Author-email: yifei.huang@gmail.com
License: UNKNOWN
Platform: UNKNOWN
Classifier: Programming Language :: Python :: 3
Classifier: License :: OSI Approved :: MIT License
Classifier: Operating System :: OS Independent
Requires-Dist: pandas
Requires-Dist: plotly
Requires-Dist: ipywidgets
Requires-Dist: IPython
